macrostrat/utils/__init__.py
macrostrat/utils/exc.py
macrostrat/utils/logs.py
macrostrat/utils/shell.py
macrostrat/utils/timer.py
macrostrat_utils-1.3.1.dist-info/METADATA
macrostrat_utils-1.3.1.dist-info/WHEEL
macrostrat_utils-1.3.1.dist-info/RECORD
