Metadata-Version: 2.3
Name: macrostrat.utils
Version: 1.3.1
Summary: Core utilities for Macrostrat and Sparrow
Author: Daven Quinn
Author-email: dev@davenquinn.com
Requires-Python: >=3.8,<4.0
Classifier: Programming Language :: Python :: 3
Classifier: Programming Language :: Python :: 3.8
Classifier: Programming Language :: Python :: 3.9
Classifier: Programming Language :: Python :: 3.10
Classifier: Programming Language :: Python :: 3.11
Classifier: Programming Language :: Python :: 3.12
Classifier: Programming Language :: Python :: 3.13
Requires-Dist: colorlog (>=6.5.0,<7.0.0)
Requires-Dist: pydantic (>=1.10.4,<3.0.0)
